CHANGES.rst
MANIFEST.in
README.rst
setup.cfg
setup.py
mxsniff/__init__.py
mxsniff/_version.py
mxsniff/providers.py
mxsniff.egg-info/PKG-INFO
mxsniff.egg-info/SOURCES.txt
mxsniff.egg-info/dependency_links.txt
mxsniff.egg-info/entry_points.txt
mxsniff.egg-info/requires.txt
mxsniff.egg-info/top_level.txt
mxsniff.egg-info/zip-safe