Metadata-Version: 1.1
Name: mxsniff
Version: 0.3.4
Summary: MX Sniffer
Home-page: https://github.com/jace/mxsniff
Author: Kiran Jonnalagadda
Author-email: jace@pobox.com
License: UNKNOWN
Keywords: mxsniff,email,mx
Platform: UNKNOWN
Classifier: Programming Language :: Python
Classifier: Programming Language :: Python :: 2.7
Classifier: Programming Language :: Python :: 3.3
Classifier: Programming Language :: Python :: 3.4
Classifier: Programming Language :: Python :: 3.5
Classifier: Programming Language :: Python :: 3.6
Classifier: License :: OSI Approved :: BSD License
Classifier: Operating System :: OS Independent
Classifier: Intended Audience :: Developers
Classifier: Development Status :: 3 - Alpha
Classifier: Topic :: Software Development :: Libraries
